setup.py
anora/__init__.py
anora/models.py
anora/tests.py
anora.egg-info/PKG-INFO
anora.egg-info/SOURCES.txt
anora.egg-info/dependency_links.txt
anora.egg-info/top_level.txt
anora/templatetags/__init__.py
anora/templatetags/anora.py