Metadata-Version: 1.0
Name: anora
Version: 0.1.2
Summary: Anora is a simple_tag for Django that determines whether or not a word should have an "a" or "an" in front of it. Adds either one of these depending on the phoentic value of the given text.
Home-page: https://github.com/juliaelman/anora
Author: Julia Elman
Author-email: julia.elman@gmail.com
License: BSD
Platform: UNKNOWN
Classifier: Topic :: Internet :: WWW/HTTP :: Dynamic Content
Classifier: Intended Audience :: Developers
Classifier: Programming Language :: Python
Classifier: Programming Language :: Python :: 2.5
Classifier: Programming Language :: Python :: 2.6
Classifier: Programming Language :: Python :: 2.7
Classifier: Topic :: Software Development :: Libraries :: Python Modules
Classifier: Development Status :: 4 - Beta
Classifier: Operating System :: OS Independent
